LICENSE
MANIFEST.in
README.md
requirements.txt
setup.cfg
setup.py
doc/LatentDirichletAllocation.rst
doc/Makefile
doc/conf.py
doc/datasets.rst
doc/index.rst
doc/lda_model.rst
doc/make.bat
doc/preprocessing.rst
doc/quick_start.rst
doc/visualization.rst
doc/images/format.PNG
doc/images/lda_model.png
doc/images/visualize1.JPG
doc/images/visualize2.JPG
doc/images/visualize3.JPG
doc/methods/ml_cgs.rst
doc/methods/ml_fw.rst
doc/methods/ml_ope.rst
doc/methods/online_cgs.rst
doc/methods/online_cvb0.rst
doc/methods/online_fw.rst
doc/methods/online_ope.rst
doc/methods/online_vb.rst
doc/methods/streaming_fw.rst
doc/methods/streaming_ope.rst
doc/methods/streaming_vb.rst
examples/__init__.py
examples/ap/example.py
examples/ap/preprocessing.py
examples/ap/data/__init__.py
examples/ap/data/ap_infer.txt
examples/ap/data/ap_infer_raw.txt
examples/ap/data/ap_train.txt
examples/ap/data/ap_train_raw.txt
examples/ap/data/vocab.txt
examples/wikipedia/run_wiki_stream.py
examples/wikipedia/wiki_stream.py
examples/wikipedia/data/vocab.txt
tmlib/__init__.py
tmlib.egg-info/PKG-INFO
tmlib.egg-info/SOURCES.txt
tmlib.egg-info/dependency_links.txt
tmlib.egg-info/requires.txt
tmlib.egg-info/top_level.txt
tmlib/datasets/__init__.py
tmlib/datasets/dataset.py
tmlib/datasets/utilizies.py
tmlib/lda/ML_CGS.py
tmlib/lda/ML_FW.py
tmlib/lda/ML_OPE.py
tmlib/lda/Online_CGS.py
tmlib/lda/Online_CVB0.py
tmlib/lda/Online_FW.py
tmlib/lda/Online_OPE.py
tmlib/lda/Online_VB.py
tmlib/lda/Streaming_FW.py
tmlib/lda/Streaming_OPE.py
tmlib/lda/Streaming_VB.py
tmlib/lda/__init__.py
tmlib/lda/ldalearning.py
tmlib/lda/ldamodel.py
tmlib/lda/utils/__init__.py
tmlib/lda/utils/util_funcs.pyx
tmlib/preprocessing/__init__.py
tmlib/preprocessing/preprocessing.py
tmlib/preprocessing/stop_word_list.txt
tmlib/visualization/__init__.py
tmlib/visualization/database.py
tmlib/visualization/visual_topics.py