Metadata-Version: 1.0
Name: tmlib
Version: 0.2.2
Summary: This is a LDA Package
Home-page: https://github.com/hncuong/topicmodel-lib
Author: dslab topicmodel-tmlib team
Author-email: truongkhang95@gmail.com
License: MIT
Keywords: ordination,LDA,topic modeling
Platform: UNKNOWN
